tud_template/__init__.py
tud_template/static/tudelft_style.css
tud_template-0.0.1.dist-info/METADATA
tud_template-0.0.1.dist-info/WHEEL
tud_template-0.0.1.dist-info/licenses/LICENSE
tud_template-0.0.1.dist-info/RECORD
