Metadata-Version: 2.3
Name: tud-template
Version: 0.0.1
Summary: A custom Sphinx extension to apply TU Delft styling to a TeachBook
Author-email: Jakub Fręchowicz <j.s.frechowicz@student.tudelft.nl>
License: MIT License
Requires-Python: >=3.10
Requires-Dist: sphinx
